persianutils/ArabicAlphabet.py
persianutils/PersianAlphabet.py
persianutils/__init__.py
persianutils/processes.py
persianutils-1.0.0.dist-info/LICENSE
persianutils-1.0.0.dist-info/METADATA
persianutils-1.0.0.dist-info/WHEEL
persianutils-1.0.0.dist-info/top_level.txt
persianutils-1.0.0.dist-info/RECORD
