Metadata-Version: 2.1
Name: persianutils
Version: 1.0.0
Summary: Standardize your Persian text: Preprocessing, Embedding, and more!
Home-page: https://github.com/ishto7/persianutils
Author: Iman Nazari
Author-email: imannazari@hotmail.com
Classifier: Programming Language :: Python :: 3
Classifier: License :: OSI Approved :: MIT License
Classifier: Operating System :: OS Independent
Requires-Python: >=3.6
License-File: LICENSE
